DAmonitor/__init__.py
DAmonitor/base.py
DAmonitor/shapes.py
pydamonitor-0.1.1.dist-info/licenses/LICENSE
pydamonitor-0.1.1.dist-info/METADATA
pydamonitor-0.1.1.dist-info/WHEEL
pydamonitor-0.1.1.dist-info/top_level.txt
pydamonitor-0.1.1.dist-info/RECORD
