Metadata-Version: 2.4
Name: pyDAmonitor
Version: 0.1.1
Summary: Safeguard invaluable DA investments by vigilantly monitoring DA performance
Author: Guoqing Ge, Junjun Hu, Aiden Pape, Ethan Wiese, Haidao Lin, Sijie Pan, Chunhua Zhou, Liaofan Lin, Terra Ladwig
Maintainer-email: Guoqing Ge <Guoqing.Ge@noaa.gov>
Project-URL: Homepage, https://pydamonitor.github.io/docs/intro.html
Project-URL: Source, https://github.com/pyDAmonitor/pyDAmonitor
Project-URL: Wiki, https://github.com/pyDAmonitor/pyDAmonitor/wiki
Project-URL: Tracker, https://github.com/pyDAmonitor/pyDAmonitor/issues
Requires-Python: >=3.9
License-File: LICENSE
Dynamic: license-file
